setup.py
client/__init__.py
client/client.py
client/client/__init__.py
client/client/add_contact.py
client/client/db_client.py
client/client/del_contact.py
client/client/main_window.py
client/client/main_window_conv.py
client/client/start_dialog.py
client/client/transport.py
client/common/__init__.py
client/common/deskriptors.py
client/common/errors.py
client/common/my_decorators.py
client/common/my_metaclasses.py
client/common/utils.py
client/common/variables.py
client/my_tests/__init__.py
client/my_tests/my_test_client.py
client/my_tests/my_test_server.py
messangerC.egg-info/PKG-INFO
messangerC.egg-info/SOURCES.txt
messangerC.egg-info/dependency_links.txt
messangerC.egg-info/requires.txt
messangerC.egg-info/top_level.txt