Metadata-Version: 1.0
Name: messangerC
Version: 0.0.1
Summary: messangerC
Home-page: UNKNOWN
Author: GalAR
Author-email: galina_87@mail.ru
License: UNKNOWN
Platform: UNKNOWN
